unittest_mocker/__init__.py
unittest_mocker/class_patcher.py
unittest_mocker/mocker.py
unittest_mocker/standart_patcher.py
unittest_mocker-0.9.0.dist-info/LICENSE
unittest_mocker-0.9.0.dist-info/METADATA
unittest_mocker-0.9.0.dist-info/WHEEL
unittest_mocker-0.9.0.dist-info/top_level.txt
unittest_mocker-0.9.0.dist-info/RECORD
